neuroflux/__init__.py
neuroflux/ct.py
neuroflux/mri.py
neuroflux-2.4.dist-info/METADATA
neuroflux-2.4.dist-info/WHEEL
neuroflux-2.4.dist-info/top_level.txt
neuroflux-2.4.dist-info/RECORD
