Metadata-Version: 2.4
Name: neuroflux
Version: 2.4
Summary: MRI and CT Brain Tumor Diagnosis and Grad-CAM Visualization
Home-page: https://github.com/Neuroflux-AI/neuroflux
Requires-Dist: matplotlib
Requires-Dist: numpy
Requires-Dist: nibabel
Requires-Dist: opencv-python
Requires-Dist: Pillow
Requires-Dist: tensorflow>=2.0
Requires-Dist: torch
Requires-Dist: torchvision
Dynamic: description
Dynamic: description-content-type
Dynamic: home-page
Dynamic: requires-dist
Dynamic: summary
